[{"kind": "Listing", "data": {"modhash": "", "dist": 1, "children": [{"kind": "t3", "data": {"approved_at_utc": null, "subreddit": "wholesomememes", "selftext": "", "user_reports": [], "saved": false, "mod_reason_title": null, "gilded": 0, "clicked": false, "title": "It\u2019s all part of your growth", "link_flair_richtext": [], "subreddit_name_prefixed": "r/wholesomememes", "hidden": false, "pwls": 6, "link_flair_css_class": null, "downs": 0, "thumbnail_height": 133, "parent_whitelist_status": "all_ads", "hide_score": false, "name": "t3_gjffgn", "quarantine": false, "link_flair_text_color": "dark", "upvote_ratio": 0.98, "author_flair_background_color": null, "subreddit_type": "public", "ups": 209, "total_awards_received": 0, "media_embed": {}, "thumbnail_width": 140, "author_flair_template_id": null, "is_original_content": false, "author_fullname": "t2_7qas4", "secure_media": null, "is_reddit_media_domain": true, "is_meta": false, "category": null, "secure_media_embed": {}, "link_flair_text": null, "can_mod_post": false, "num_duplicates": 0, "approved_by": null, "author_premium": false, "thumbnail": "https://a.thumbs.redditmedia.com/OY6tE0oqgHQoNOHvHojIPniA8hK5fLtcH396NYje-74.jpg", "edited": false, "author_flair_css_class": null, "author_flair_richtext": [], "gildings": {}, "post_hint": "image", "content_categories": null, "is_self": false, "mod_note": null, "created": 1589459960.0, "link_flair_type": "text", "wls": 6, "removed_by_category": null, "banned_by": null, "author_flair_type": "text", "domain": "i.redd.it", "allow_live_comments": false, "selftext_html": null, "likes": null, "suggested_sort": null, "banned_at_utc": null, "view_count": null, "archived": false, "score": 209, "no_follow": false, "is_crosspostable": false, "pinned": false, "over_18": false, "preview": {"images": [{"source": {"url": "https://preview.redd.it/y0e5kzjbtny41.jpg?auto=webp&s=3e376a61e8da36fb8b15b0cff72356fb85261152", "width": 1052, "height": 1003}, "resolutions": [{"url": "https://preview.redd.it/y0e5kzjbtny41.jpg?width=108&crop=smart&auto=webp&s=d5fe6f2534171b63cb199e09c7a94677140e8203", "width": 108, "height": 102}, {"url": "https://preview.redd.it/y0e5kzjbtny41.jpg?width=216&crop=smart&auto=webp&s=362707166a8e7af0e970bacf66fed0426486db92", "width": 216, "height": 205}, {"url": "https://preview.redd.it/y0e5kzjbtny41.jpg?width=320&crop=smart&auto=webp&s=cb7fccf424eed8b2a75f0581d6e9451657015e32", "width": 320, "height": 305}, {"url": "https://preview.redd.it/y0e5kzjbtny41.jpg?width=640&crop=smart&auto=webp&s=35711f89c1b4882793962870e5574f99a9f9f7ae", "width": 640, "height": 610}, {"url": "https://preview.redd.it/y0e5kzjbtny41.jpg?width=960&crop=smart&auto=webp&s=fcaa332fb61fc45ca28c0dfa0fe0e0449fb4950f", "width": 960, "height": 915}], "variants": {}, "id": "DXagEDIS25hB6j-HmSofXsI0SYpuE2SW3KRy_RIUH8c"}], "enabled": true}, "all_awardings": [], "awarders": [], "media_only": false, "can_gild": false, "spoiler": false, "locked": false, "author_flair_text": null, "treatment_tags": [], "visited": false, "removed_by": null, "num_reports": null, "distinguished": null, "subreddit_id": "t5_3gcwj", "mod_reason_by": null, "removal_reason": null, "link_flair_background_color": "", "id": "gjffgn", "is_robot_indexable": true, "report_reasons": null, "author": "moshinator94", "discussion_type": null, "num_comments": 5, "send_replies": true, "media": null, "contest_mode": false, "author_patreon_flair": false, "author_flair_text_color": null, "permalink": "/r/wholesomememes/comments/gjffgn/its_all_part_of_your_growth/", "whitelist_status": "all_ads", "stickied": false, "url": "https://i.redd.it/y0e5kzjbtny41.jpg", "subreddit_subscribers": 6986352, "created_utc": 1589431160.0, "num_crossposts": 0, "mod_reports": [], "is_video": false}}], "after": null, "before": null}}, {"kind": "Listing", "data": {"modhash": "", "dist": null, "children": [{"kind": "t1", "data": {"total_awards_received": 0, "approved_at_utc": null, "ups": 3, "awarders": [], "mod_reason_by": null, "banned_by": null, "author_flair_type": "text", "removal_reason": null, "link_id": "t3_gjffgn", "author_flair_template_id": null, "likes": null, "replies": {"kind": "Listing", "data": {"modhash": "", "dist": null, "children": [{"kind": "t1", "data": {"total_awards_received": 1, "approved_at_utc": null, "ups": 4, "awarders": [], "mod_reason_by": null, "banned_by": null, "author_flair_type": "text", "removal_reason": null, "link_id": "t3_gjffgn", "author_flair_template_id": null, "likes": null, "replies": "", "user_reports": [], "saved": false, "id": "fqkno7g", "banned_at_utc": null, "mod_reason_title": null, "gilded": 0, "archived": false, "no_follow": true, "author": "moshinator94", "can_mod_post": false, "send_replies": true, "parent_id": "t1_fqknkdw", "score": 4, "author_fullname": "t2_7qas4", "report_reasons": null, "approved_by": null, "all_awardings": [{"giver_coin_reward": 0, "subreddit_id": null, "is_new": false, "days_of_drip_extension": 0, "coin_price": 30, "id": "award_a903c949-ccc5-420d-8239-1bbefc424838", "penny_donate": 0, "coin_reward": 0, "icon_url": "https://i.redd.it/award_images/t5_22cerq/xs2na1t1v9p41_HealthcareHero.png", "days_of_premium": 0, "icon_height": 2048, "resized_icons": [{"url": "https://preview.redd.it/award_images/t5_22cerq/xs2na1t1v9p41_HealthcareHero.png?width=16&height=16&auto=webp&s=b5fef44e8d43a8e96598192b046697458d40b105", "width": 16, "height": 16}, {"url": "https://preview.redd.it/award_images/t5_22cerq/xs2na1t1v9p41_HealthcareHero.png?width=32&height=32&auto=webp&s=1ac04c3fc6fa558695baf5d534aa1756aa651459", "width": 32, "height": 32}, {"url": "https://preview.redd.it/award_images/t5_22cerq/xs2na1t1v9p41_HealthcareHero.png?width=48&height=48&auto=webp&s=111f12637505e5dea857caf5b3cdec196ddb7377", "width": 48, "height": 48}, {"url": "https://preview.redd.it/award_images/t5_22cerq/xs2na1t1v9p41_HealthcareHero.png?width=64&height=64&auto=webp&s=fe0a80824f28b6f20218d8a83a2ea15548bbbaab", "width": 64, "height": 64}, {"url": "https://preview.redd.it/award_images/t5_22cerq/xs2na1t1v9p41_HealthcareHero.png?width=128&height=128&auto=webp&s=60527ab68ff6bf227a3523f588441f0b5d127c54", "width": 128, "height": 128}], "icon_width": 2048, "start_date": null, "is_enabled": true, "description": "Putting yourself on the line for us - you are the perfect super hero!", "end_date": null, "subreddit_coin_reward": 0, "count": 1, "name": "Healthcare Hero", "icon_format": "PNG", "award_sub_type": "GLOBAL", "penny_price": 0, "award_type": "global"}], "subreddit_id": "t5_3gcwj", "collapsed": false, "body": "Whatever it is you\u2019re going through friend, you\u2019re gonna come out a stronger person! All the best.", "edited": false, "author_flair_css_class": null, "is_submitter": true, "downs": 0, "author_flair_richtext": [], "author_patreon_flair": false, "body_html": "<div class=\"md\"><p>Whatever it is you\u2019re going through friend, you\u2019re gonna come out a stronger person! All the best.</p>\n</div>", "gildings": {}, "collapsed_reason": null, "associated_award": null, "stickied": false, "author_premium": false, "subreddit_type": "public", "can_gild": true, "subreddit": "wholesomememes", "author_flair_text_color": null, "score_hidden": false, "permalink": "/r/wholesomememes/comments/gjffgn/its_all_part_of_your_growth/fqkno7g/", "num_reports": null, "locked": false, "name": "t1_fqkno7g", "created": 1589460261.0, "author_flair_text": null, "treatment_tags": [], "created_utc": 1589431461.0, "subreddit_name_prefixed": "r/wholesomememes", "controversiality": 0, "depth": 1, "author_flair_background_color": null, "collapsed_because_crowd_control": null, "mod_reports": [], "mod_note": null, "distinguished": null}}], "after": null, "before": null}}, "user_reports": [], "saved": false, "id": "fqknkdw", "banned_at_utc": null, "mod_reason_title": null, "gilded": 0, "archived": false, "no_follow": true, "author": "raqoonz", "can_mod_post": false, "send_replies": true, "parent_id": "t3_gjffgn", "score": 3, "author_fullname": "t2_297xgopv", "report_reasons": null, "approved_by": null, "all_awardings": [], "subreddit_id": "t5_3gcwj", "body": "I needed this tonight.  Thank you :)", "edited": false, "downs": 0, "author_flair_css_class": null, "is_submitter": false, "collapsed": false, "author_flair_richtext": [], "author_patreon_flair": false, "body_html": "<div class=\"md\"><p>I needed this tonight.  Thank you :)</p>\n</div>", "gildings": {}, "collapsed_reason": null, "associated_award": null, "stickied": false, "author_premium": false, "subreddit_type": "public", "can_gild": true, "subreddit": "wholesomememes", "author_flair_text_color": null, "score_hidden": false, "permalink": "/r/wholesomememes/comments/gjffgn/its_all_part_of_your_growth/fqknkdw/", "num_reports": null, "locked": false, "name": "t1_fqknkdw", "created": 1589460188.0, "author_flair_text": null, "treatment_tags": [], "created_utc": 1589431388.0, "subreddit_name_prefixed": "r/wholesomememes", "controversiality": 0, "depth": 0, "author_flair_background_color": null, "collapsed_because_crowd_control": null, "mod_reports": [], "mod_note": null, "distinguished": null}}, {"kind": "t1", "data": {"total_awards_received": 0, "approved_at_utc": null, "ups": 1, "awarders": [], "mod_reason_by": null, "banned_by": null, "author_flair_type": "text", "removal_reason": null, "link_id": "t3_gjffgn", "author_flair_template_id": null, "likes": null, "replies": "", "user_reports": [], "saved": false, "id": "fqkuz8s", "banned_at_utc": null, "mod_reason_title": null, "gilded": 0, "archived": false, "no_follow": true, "author": "jaw_daw123", "can_mod_post": false, "send_replies": true, "parent_id": "t3_gjffgn", "score": 1, "author_fullname": "t2_65ekifrj", "report_reasons": null, "approved_by": null, "all_awardings": [], "subreddit_id": "t5_3gcwj", "body": "After me and my demon are good friends imagine th pranks we could pull up", "edited": false, "downs": 0, "author_flair_css_class": null, "is_submitter": false, "collapsed": false, "author_flair_richtext": [], "author_patreon_flair": false, "body_html": "<div class=\"md\"><p>After me and my demon are good friends imagine th pranks we could pull up</p>\n</div>", "gildings": {}, "collapsed_reason": null, "associated_award": null, "stickied": false, "author_premium": false, "subreddit_type": "public", "can_gild": true, "subreddit": "wholesomememes", "author_flair_text_color": null, "score_hidden": false, "permalink": "/r/wholesomememes/comments/gjffgn/its_all_part_of_your_growth/fqkuz8s/", "num_reports": null, "locked": false, "name": "t1_fqkuz8s", "created": 1589465850.0, "author_flair_text": null, "treatment_tags": [], "created_utc": 1589437050.0, "subreddit_name_prefixed": "r/wholesomememes", "controversiality": 0, "depth": 0, "author_flair_background_color": null, "collapsed_because_crowd_control": null, "mod_reports": [], "mod_note": null, "distinguished": null}}, {"kind": "t1", "data": {"total_awards_received": 0, "approved_at_utc": null, "ups": -1, "awarders": [], "mod_reason_by": null, "banned_by": null, "author_flair_type": "text", "removal_reason": null, "link_id": "t3_gjffgn", "author_flair_template_id": null, "likes": null, "replies": "", "user_reports": [], "saved": false, "id": "fql8pwa", "banned_at_utc": null, "mod_reason_title": null, "gilded": 0, "archived": false, "no_follow": true, "author": "DataFaerie", "can_mod_post": false, "send_replies": true, "parent_id": "t3_gjffgn", "score": -1, "author_fullname": "t2_69v1ale6", "report_reasons": null, "approved_by": null, "all_awardings": [], "subreddit_id": "t5_3gcwj", "body": "My God please stop with this meme. Can't stand those pictures anymore.", "edited": false, "downs": 0, "author_flair_css_class": null, "is_submitter": false, "collapsed": false, "author_flair_richtext": [], "author_patreon_flair": false, "body_html": "<div class=\"md\"><p>My God please stop with this meme. Can&#39;t stand those pictures anymore.</p>\n</div>", "gildings": {}, "collapsed_reason": null, "associated_award": null, "stickied": false, "author_premium": false, "subreddit_type": "public", "can_gild": true, "subreddit": "wholesomememes", "author_flair_text_color": null, "score_hidden": false, "permalink": "/r/wholesomememes/comments/gjffgn/its_all_part_of_your_growth/fql8pwa/", "num_reports": null, "locked": false, "name": "t1_fql8pwa", "created": 1589479010.0, "author_flair_text": null, "treatment_tags": [], "created_utc": 1589450210.0, "subreddit_name_prefixed": "r/wholesomememes", "controversiality": 0, "depth": 0, "author_flair_background_color": null, "collapsed_because_crowd_control": null, "mod_reports": [], "mod_note": null, "distinguished": null}}], "after": null, "before": null}}]