[{"kind": "Listing", "data": {"modhash": "", "dist": 1, "children": [{"kind": "t3", "data": {"approved_at_utc": null, "subreddit": "awfuleverything", "selftext": "", "user_reports": [], "saved": false, "mod_reason_title": null, "gilded": 0, "clicked": false, "title": "Shitty food porn", "link_flair_richtext": [], "subreddit_name_prefixed": "r/awfuleverything", "hidden": false, "pwls": 1, "link_flair_css_class": null, "downs": 0, "thumbnail_height": 140, "parent_whitelist_status": "house_only", "hide_score": false, "name": "t3_gjfwar", "quarantine": false, "link_flair_text_color": "dark", "upvote_ratio": 0.99, "author_flair_background_color": null, "subreddit_type": "public", "ups": 102, "total_awards_received": 0, "media_embed": {}, "thumbnail_width": 140, "author_flair_template_id": null, "is_original_content": false, "author_fullname": "t2_4j3bl0vj", "secure_media": null, "is_reddit_media_domain": true, "is_meta": false, "category": null, "secure_media_embed": {}, "link_flair_text": null, "can_mod_post": false, "num_duplicates": 5, "approved_by": null, "author_premium": false, "thumbnail": "https://b.thumbs.redditmedia.com/4tVYDOD36aZMH5YQp95hgkhNUoVYfiHupovwSow2wvQ.jpg", "edited": false, "author_flair_css_class": null, "author_flair_richtext": [], "gildings": {}, "post_hint": "image", "content_categories": null, "is_self": false, "mod_note": null, "crosspost_parent_list": [{"approved_at_utc": null, "subreddit": "MakeMeSuffer", "selftext": "", "user_reports": [], "saved": false, "mod_reason_title": null, "gilded": 0, "clicked": false, "title": "Shitty food porn", "link_flair_richtext": [], "subreddit_name_prefixed": "r/MakeMeSuffer", "hidden": false, "pwls": null, "link_flair_css_class": null, "downs": 0, "thumbnail_height": 140, "parent_whitelist_status": null, "hide_score": false, "name": "t3_giyjvh", "quarantine": false, "link_flair_text_color": "dark", "upvote_ratio": 0.99, "author_flair_background_color": "#1a1a1b", "subreddit_type": "public", "ups": 4054, "total_awards_received": 0, "media_embed": {}, "thumbnail_width": 140, "author_flair_template_id": "73d29804-6e04-11ea-b7a0-0ecb2ae266bf", "is_original_content": false, "author_fullname": "t2_f08ztfa", "secure_media": null, "is_reddit_media_domain": true, "is_meta": false, "category": null, "secure_media_embed": {}, "link_flair_text": null, "can_mod_post": false, "score": 4054, "approved_by": null, "author_premium": true, "thumbnail": "https://b.thumbs.redditmedia.com/4tVYDOD36aZMH5YQp95hgkhNUoVYfiHupovwSow2wvQ.jpg", "edited": false, "author_flair_css_class": null, "author_flair_richtext": [{"e": "text", "t": "Dark Flair"}], "gildings": {}, "post_hint": "image", "content_categories": null, "is_self": false, "mod_note": null, "created": 1589403583.0, "link_flair_type": "text", "wls": null, "removed_by_category": null, "banned_by": null, "author_flair_type": "richtext", "domain": "i.redd.it", "allow_live_comments": false, "selftext_html": null, "likes": null, "suggested_sort": null, "banned_at_utc": null, "view_count": null, "archived": false, "no_follow": false, "is_crosspostable": false, "pinned": false, "over_18": false, "preview": {"images": [{"source": {"url": "https://preview.redd.it/7klzqkqp5jy41.jpg?auto=webp&s=9758cbe6ca6f918fca90e988dfa6fcc255cd0750", "width": 1440, "height": 2017}, "resolutions": [{"url": "https://preview.redd.it/7klzqkqp5jy41.jpg?width=108&crop=smart&auto=webp&s=cef05d19d7c8d70bc2aa05b0d8d1b8c33d9acfab", "width": 108, "height": 151}, {"url": "https://preview.redd.it/7klzqkqp5jy41.jpg?width=216&crop=smart&auto=webp&s=8db8a9b6aff4da9b31a4a978ccbb991ddc2c1a8e", "width": 216, "height": 302}, {"url": "https://preview.redd.it/7klzqkqp5jy41.jpg?width=320&crop=smart&auto=webp&s=b5ec344d1c260c64d4f9a96f699834cc51ac665f", "width": 320, "height": 448}, {"url": "https://preview.redd.it/7klzqkqp5jy41.jpg?width=640&crop=smart&auto=webp&s=e579527abd7661e7e9b9a769a247d06aa7447716", "width": 640, "height": 896}, {"url": "https://preview.redd.it/7klzqkqp5jy41.jpg?width=960&crop=smart&auto=webp&s=a34bed4f77a25062524ab7494dae7e605c6a198d", "width": 960, "height": 1344}, {"url": "https://preview.redd.it/7klzqkqp5jy41.jpg?width=1080&crop=smart&auto=webp&s=bb8bef5a17953a5269bbf3fea0c48053841e3be1", "width": 1080, "height": 1512}], "variants": {}, "id": "JLf7F6dd9TjavG0Pi8jfclkJB96Dqm4Fr-fHeuvCYiE"}], "enabled": true}, "all_awardings": [], "awarders": [], "media_only": false, "can_gild": false, "spoiler": false, "locked": false, "author_flair_text": "Dark Flair", "treatment_tags": [], "visited": false, "removed_by": null, "num_reports": null, "distinguished": null, "subreddit_id": "t5_mf29x", "mod_reason_by": null, "removal_reason": null, "link_flair_background_color": "", "id": "giyjvh", "is_robot_indexable": true, "report_reasons": null, "author": "ATJWen", "discussion_type": null, "num_comments": 89, "send_replies": true, "media": null, "contest_mode": false, "author_patreon_flair": false, "author_flair_text_color": "light", "permalink": "/r/MakeMeSuffer/comments/giyjvh/shitty_food_porn/", "whitelist_status": null, "stickied": false, "url": "https://i.redd.it/7klzqkqp5jy41.jpg", "subreddit_subscribers": 711548, "created_utc": 1589374783.0, "num_crossposts": 4, "mod_reports": [], "is_video": false}], "created": 1589462058.0, "link_flair_type": "text", "wls": 1, "removed_by_category": null, "banned_by": null, "author_flair_type": "text", "domain": "i.redd.it", "allow_live_comments": false, "selftext_html": null, "likes": null, "suggested_sort": null, "banned_at_utc": null, "view_count": null, "archived": false, "score": 102, "no_follow": false, "is_crosspostable": false, "pinned": false, "over_18": false, "preview": {"images": [{"source": {"url": "https://preview.redd.it/7klzqkqp5jy41.jpg?auto=webp&s=9758cbe6ca6f918fca90e988dfa6fcc255cd0750", "width": 1440, "height": 2017}, "resolutions": [{"url": "https://preview.redd.it/7klzqkqp5jy41.jpg?width=108&crop=smart&auto=webp&s=cef05d19d7c8d70bc2aa05b0d8d1b8c33d9acfab", "width": 108, "height": 151}, {"url": "https://preview.redd.it/7klzqkqp5jy41.jpg?width=216&crop=smart&auto=webp&s=8db8a9b6aff4da9b31a4a978ccbb991ddc2c1a8e", "width": 216, "height": 302}, {"url": "https://preview.redd.it/7klzqkqp5jy41.jpg?width=320&crop=smart&auto=webp&s=b5ec344d1c260c64d4f9a96f699834cc51ac665f", "width": 320, "height": 448}, {"url": "https://preview.redd.it/7klzqkqp5jy41.jpg?width=640&crop=smart&auto=webp&s=e579527abd7661e7e9b9a769a247d06aa7447716", "width": 640, "height": 896}, {"url": "https://preview.redd.it/7klzqkqp5jy41.jpg?width=960&crop=smart&auto=webp&s=a34bed4f77a25062524ab7494dae7e605c6a198d", "width": 960, "height": 1344}, {"url": "https://preview.redd.it/7klzqkqp5jy41.jpg?width=1080&crop=smart&auto=webp&s=bb8bef5a17953a5269bbf3fea0c48053841e3be1", "width": 1080, "height": 1512}], "variants": {}, "id": "JLf7F6dd9TjavG0Pi8jfclkJB96Dqm4Fr-fHeuvCYiE"}], "enabled": true}, "all_awardings": [], "awarders": [], "media_only": false, "can_gild": false, "spoiler": false, "locked": false, "author_flair_text": null, "treatment_tags": [], "visited": false, "removed_by": null, "num_reports": null, "distinguished": null, "subreddit_id": "t5_346d4", "mod_reason_by": null, "removal_reason": null, "link_flair_background_color": "", "id": "gjfwar", "is_robot_indexable": true, "report_reasons": null, "author": "LoveAllis", "discussion_type": null, "num_comments": 7, "send_replies": true, "media": null, "contest_mode": false, "author_patreon_flair": false, "crosspost_parent": "t3_giyjvh", "author_flair_text_color": null, "permalink": "/r/awfuleverything/comments/gjfwar/shitty_food_porn/", "whitelist_status": "house_only", "stickied": false, "url": "https://i.redd.it/7klzqkqp5jy41.jpg", "subreddit_subscribers": 900375, "created_utc": 1589433258.0, "num_crossposts": 0, "mod_reports": [], "is_video": false}}], "after": null, "before": null}}, {"kind": "Listing", "data": {"modhash": "", "dist": null, "children": [{"kind": "t1", "data": {"total_awards_received": 0, "approved_at_utc": null, "ups": 5, "awarders": [], "mod_reason_by": null, "banned_by": null, "author_flair_type": "text", "removal_reason": null, "link_id": "t3_gjfwar", "author_flair_template_id": null, "likes": null, "replies": "", "user_reports": [], "saved": false, "id": "fqlg6ry", "banned_at_utc": null, "mod_reason_title": null, "gilded": 0, "archived": false, "no_follow": false, "author": "admafa", "can_mod_post": false, "send_replies": true, "parent_id": "t3_gjfwar", "score": 5, "author_fullname": "t2_24kjwbqe", "report_reasons": null, "approved_by": null, "all_awardings": [], "subreddit_id": "t5_346d4", "body": "Like a turd on a plate", "edited": false, "downs": 0, "author_flair_css_class": null, "is_submitter": false, "collapsed": false, "author_flair_richtext": [], "author_patreon_flair": false, "body_html": "<div class=\"md\"><p>Like a turd on a plate</p>\n</div>", "gildings": {}, "collapsed_reason": null, "associated_award": null, "stickied": false, "author_premium": false, "subreddit_type": "public", "can_gild": true, "subreddit": "awfuleverything", "author_flair_text_color": null, "score_hidden": false, "permalink": "/r/awfuleverything/comments/gjfwar/shitty_food_porn/fqlg6ry/", "num_reports": null, "locked": false, "name": "t1_fqlg6ry", "created": 1589485993.0, "author_flair_text": null, "treatment_tags": [], "created_utc": 1589457193.0, "subreddit_name_prefixed": "r/awfuleverything", "controversiality": 0, "depth": 0, "author_flair_background_color": null, "collapsed_because_crowd_control": null, "mod_reports": [], "mod_note": null, "distinguished": null}}, {"kind": "t1", "data": {"total_awards_received": 0, "approved_at_utc": null, "ups": 5, "awarders": [], "mod_reason_by": null, "banned_by": null, "author_flair_type": "text", "removal_reason": null, "link_id": "t3_gjfwar", "author_flair_template_id": null, "likes": null, "replies": "", "user_reports": [], "saved": false, "id": "fqkzw9c", "banned_at_utc": null, "mod_reason_title": null, "gilded": 0, "archived": false, "no_follow": false, "author": "ChromeBitchSickTrips", "can_mod_post": false, "send_replies": true, "parent_id": "t3_gjfwar", "score": 5, "author_fullname": "t2_59h68ypm", "report_reasons": null, "approved_by": null, "all_awardings": [], "subreddit_id": "t5_346d4", "body": "If it's got a leaf next to it, it's fab", "edited": false, "downs": 0, "author_flair_css_class": null, "is_submitter": false, "collapsed": false, "author_flair_richtext": [], "author_patreon_flair": false, "body_html": "<div class=\"md\"><p>If it&#39;s got a leaf next to it, it&#39;s fab</p>\n</div>", "gildings": {}, "collapsed_reason": null, "associated_award": null, "stickied": false, "author_premium": false, "subreddit_type": "public", "can_gild": true, "subreddit": "awfuleverything", "author_flair_text_color": null, "score_hidden": false, "permalink": "/r/awfuleverything/comments/gjfwar/shitty_food_porn/fqkzw9c/", "num_reports": null, "locked": false, "name": "t1_fqkzw9c", "created": 1589470275.0, "author_flair_text": null, "treatment_tags": [], "created_utc": 1589441475.0, "subreddit_name_prefixed": "r/awfuleverything", "controversiality": 0, "depth": 0, "author_flair_background_color": null, "collapsed_because_crowd_control": null, "mod_reports": [], "mod_note": null, "distinguished": null}}, {"kind": "t1", "data": {"total_awards_received": 0, "approved_at_utc": null, "ups": 2, "awarders": [], "mod_reason_by": null, "banned_by": null, "author_flair_type": "text", "removal_reason": null, "link_id": "t3_gjfwar", "author_flair_template_id": null, "likes": null, "replies": "", "user_reports": [], "saved": false, "id": "fql0mqr", "banned_at_utc": null, "mod_reason_title": null, "gilded": 0, "archived": false, "no_follow": true, "author": "amanthatdontfall", "can_mod_post": false, "send_replies": true, "parent_id": "t3_gjfwar", "score": 2, "author_fullname": "t2_5qt42efd", "report_reasons": null, "approved_by": null, "all_awardings": [], "subreddit_id": "t5_346d4", "body": "\"Who could resist that?\"", "edited": false, "downs": 0, "author_flair_css_class": null, "is_submitter": false, "collapsed": false, "author_flair_richtext": [], "author_patreon_flair": false, "body_html": "<div class=\"md\"><p>&quot;Who could resist that?&quot;</p>\n</div>", "gildings": {}, "collapsed_reason": null, "associated_award": null, "stickied": false, "author_premium": false, "subreddit_type": "public", "can_gild": true, "subreddit": "awfuleverything", "author_flair_text_color": null, "score_hidden": false, "permalink": "/r/awfuleverything/comments/gjfwar/shitty_food_porn/fql0mqr/", "num_reports": null, "locked": false, "name": "t1_fql0mqr", "created": 1589470988.0, "author_flair_text": null, "treatment_tags": [], "created_utc": 1589442188.0, "subreddit_name_prefixed": "r/awfuleverything", "controversiality": 0, "depth": 0, "author_flair_background_color": null, "collapsed_because_crowd_control": null, "mod_reports": [], "mod_note": null, "distinguished": null}}, {"kind": "t1", "data": {"total_awards_received": 0, "approved_at_utc": null, "ups": 1, "awarders": [], "mod_reason_by": null, "banned_by": null, "author_flair_type": "text", "removal_reason": null, "link_id": "t3_gjfwar", "author_flair_template_id": null, "likes": null, "replies": {"kind": "Listing", "data": {"modhash": "", "dist": null, "children": [{"kind": "t1", "data": {"total_awards_received": 0, "approved_at_utc": null, "ups": 1, "awarders": [], "mod_reason_by": null, "banned_by": null, "author_flair_type": "text", "removal_reason": null, "link_id": "t3_gjfwar", "author_flair_template_id": null, "likes": null, "replies": "", "user_reports": [], "saved": false, "id": "fqlg84h", "banned_at_utc": null, "mod_reason_title": null, "gilded": 0, "archived": false, "no_follow": true, "author": "admafa", "can_mod_post": false, "send_replies": true, "parent_id": "t1_fqlbksb", "score": 1, "author_fullname": "t2_24kjwbqe", "report_reasons": null, "approved_by": null, "all_awardings": [], "subreddit_id": "t5_346d4", "collapsed": false, "body": "Well i don't shit crispy hazelnuts bud \ud83d\ude02", "edited": false, "author_flair_css_class": null, "is_submitter": false, "downs": 0, "author_flair_richtext": [], "author_patreon_flair": false, "body_html": "<div class=\"md\"><p>Well i don&#39;t shit crispy hazelnuts bud \ud83d\ude02</p>\n</div>", "gildings": {}, "collapsed_reason": null, "associated_award": null, "stickied": false, "author_premium": false, "subreddit_type": "public", "can_gild": true, "subreddit": "awfuleverything", "author_flair_text_color": null, "score_hidden": false, "permalink": "/r/awfuleverything/comments/gjfwar/shitty_food_porn/fqlg84h/", "num_reports": null, "locked": false, "name": "t1_fqlg84h", "created": 1589486024.0, "author_flair_text": null, "treatment_tags": [], "created_utc": 1589457224.0, "subreddit_name_prefixed": "r/awfuleverything", "controversiality": 0, "depth": 1, "author_flair_background_color": null, "collapsed_because_crowd_control": null, "mod_reports": [], "mod_note": null, "distinguished": null}}, {"kind": "t1", "data": {"total_awards_received": 0, "approved_at_utc": null, "ups": 1, "awarders": [], "mod_reason_by": null, "banned_by": null, "author_flair_type": "text", "removal_reason": null, "link_id": "t3_gjfwar", "author_flair_template_id": null, "likes": null, "replies": "", "user_reports": [], "saved": false, "id": "fqmcruq", "banned_at_utc": null, "mod_reason_title": null, "gilded": 0, "archived": false, "no_follow": true, "author": "Lupus_Noir", "can_mod_post": false, "send_replies": true, "parent_id": "t1_fqlbksb", "score": 1, "author_fullname": "t2_3itt0i7a", "report_reasons": null, "approved_by": null, "all_awardings": [], "subreddit_id": "t5_346d4", "collapsed": false, "body": "Depending on the ingredients, it can be either crispy, or runny.", "edited": false, "author_flair_css_class": null, "is_submitter": false, "downs": 0, "author_flair_richtext": [], "author_patreon_flair": false, "body_html": "<div class=\"md\"><p>Depending on the ingredients, it can be either crispy, or runny.</p>\n</div>", "gildings": {}, "collapsed_reason": null, "associated_award": null, "stickied": false, "author_premium": false, "subreddit_type": "public", "can_gild": true, "subreddit": "awfuleverything", "author_flair_text_color": null, "score_hidden": false, "permalink": "/r/awfuleverything/comments/gjfwar/shitty_food_porn/fqmcruq/", "num_reports": null, "locked": false, "name": "t1_fqmcruq", "created": 1589504107.0, "author_flair_text": null, "treatment_tags": [], "created_utc": 1589475307.0, "subreddit_name_prefixed": "r/awfuleverything", "controversiality": 0, "depth": 1, "author_flair_background_color": null, "collapsed_because_crowd_control": null, "mod_reports": [], "mod_note": null, "distinguished": null}}], "after": null, "before": null}}, "user_reports": [], "saved": false, "id": "fqlbksb", "banned_at_utc": null, "mod_reason_title": null, "gilded": 0, "archived": false, "no_follow": true, "author": "NoShadowdick", "can_mod_post": false, "send_replies": true, "parent_id": "t3_gjfwar", "score": 1, "author_fullname": "t2_40jmqh5p", "report_reasons": null, "approved_by": null, "all_awardings": [], "subreddit_id": "t5_346d4", "body": "Anybody can make that. It's easy.", "edited": false, "downs": 0, "author_flair_css_class": null, "is_submitter": false, "collapsed": false, "author_flair_richtext": [], "author_patreon_flair": false, "body_html": "<div class=\"md\"><p>Anybody can make that. It&#39;s easy.</p>\n</div>", "gildings": {}, "collapsed_reason": null, "associated_award": null, "stickied": false, "author_premium": false, "subreddit_type": "public", "can_gild": true, "subreddit": "awfuleverything", "author_flair_text_color": null, "score_hidden": false, "permalink": "/r/awfuleverything/comments/gjfwar/shitty_food_porn/fqlbksb/", "num_reports": null, "locked": false, "name": "t1_fqlbksb", "created": 1589481843.0, "author_flair_text": null, "treatment_tags": [], "created_utc": 1589453043.0, "subreddit_name_prefixed": "r/awfuleverything", "controversiality": 0, "depth": 0, "author_flair_background_color": null, "collapsed_because_crowd_control": null, "mod_reports": [], "mod_note": null, "distinguished": null}}, {"kind": "t1", "data": {"total_awards_received": 0, "approved_at_utc": null, "ups": 1, "awarders": [], "mod_reason_by": null, "banned_by": null, "author_flair_type": "text", "removal_reason": null, "link_id": "t3_gjfwar", "author_flair_template_id": null, "likes": null, "replies": "", "user_reports": [], "saved": false, "id": "fqlhl46", "banned_at_utc": null, "mod_reason_title": null, "gilded": 0, "archived": false, "no_follow": true, "author": "NoShadowdick", "can_mod_post": false, "send_replies": true, "parent_id": "t3_gjfwar", "score": 1, "author_fullname": "t2_40jmqh5p", "report_reasons": null, "approved_by": null, "all_awardings": [], "subreddit_id": "t5_346d4", "body": "LMAO! Anything is possible. Practice makes perfect.", "edited": false, "downs": 0, "author_flair_css_class": null, "is_submitter": false, "collapsed": false, "author_flair_richtext": [], "author_patreon_flair": false, "body_html": "<div class=\"md\"><p>LMAO! Anything is possible. Practice makes perfect.</p>\n</div>", "gildings": {}, "collapsed_reason": null, "associated_award": null, "stickied": false, "author_premium": false, "subreddit_type": "public", "can_gild": true, "subreddit": "awfuleverything", "author_flair_text_color": null, "score_hidden": false, "permalink": "/r/awfuleverything/comments/gjfwar/shitty_food_porn/fqlhl46/", "num_reports": null, "locked": false, "name": "t1_fqlhl46", "created": 1589487106.0, "author_flair_text": null, "treatment_tags": [], "created_utc": 1589458306.0, "subreddit_name_prefixed": "r/awfuleverything", "controversiality": 0, "depth": 0, "author_flair_background_color": null, "collapsed_because_crowd_control": null, "mod_reports": [], "mod_note": null, "distinguished": null}}], "after": null, "before": null}}]